README.md
setup.py
Tsnewp/GeValue.py
Tsnewp/Tsnewp.py
Tsnewp/__init__.py
Tsnewp/_pca.py
Tsnewp.egg-info/PKG-INFO
Tsnewp.egg-info/SOURCES.txt
Tsnewp.egg-info/dependency_links.txt
Tsnewp.egg-info/top_level.txt